xaif/__init__.py
xaif/xaif.py
xaif/xaif_templates.py
xaif-0.3.6.dist-info/METADATA
xaif-0.3.6.dist-info/WHEEL
xaif-0.3.6.dist-info/RECORD
