Metadata-Version: 2.4
Name: xaif
Version: 0.3.6
Summary: xaif package
Project-URL: Homepage, https://github.com/arg-tech/xaif
Project-URL: Issues, https://github.com/arg-tech/xaif/issues
Author-email: DEBELA <dabookoo@gmail.com>
Classifier: License :: OSI Approved :: MIT License
Classifier: Operating System :: OS Independent
Classifier: Programming Language :: Python :: 3
Requires-Python: >=3.8
